graphtec/__init__.py
graphtec/_version.py
graphtec/api/__init__.py
graphtec/api/public.py
graphtec/connection/__init__.py
graphtec/connection/base.py
graphtec/connection/serial_connection.py
graphtec/connection/wlan_connection.py
graphtec/core/__init__.py
graphtec/core/commands.py
graphtec/core/exceptions.py
graphtec/core/device/__init__.py
graphtec/core/device/alarm.py
graphtec/core/device/amp.py
graphtec/core/device/base.py
graphtec/core/device/common.py
graphtec/core/device/data.py
graphtec/core/device/file.py
graphtec/core/device/interface.py
graphtec/core/device/logic.py
graphtec/core/device/measure.py
graphtec/core/device/option.py
graphtec/core/device/status.py
graphtec/core/device/transfer.py
graphtec/core/device/trigger.py
graphtec/io/__init__.py
graphtec/io/capture.py
graphtec/io/decoder.py
graphtec/io/realtime.py
graphtec/utils/__init__.py
graphtec/utils/conn_monitor.py
graphtec/utils/logger.py
graphtec/utils/utils.py
graphtec_api-1.0.0.dist-info/licenses/LICENSE
graphtec_api-1.0.0.dist-info/METADATA
graphtec_api-1.0.0.dist-info/WHEEL
graphtec_api-1.0.0.dist-info/top_level.txt
graphtec_api-1.0.0.dist-info/RECORD
