Metadata-Version: 2.4
Name: graphtec-api
Version: 1.0.0
Summary: Librería en Python para el control y adquisición de datos del Datalogger GL100
Author-email: Miguel Chen Zheng <tu_email_universidad@alumnos.upm.es>
Project-URL: Homepage, https://github.com/miguel-cz/graphtec-api
Project-URL: Bug Tracker, https://github.com/miguel-cz/graphtec-api/issues
Classifier: Programming Language :: Python :: 3
Classifier: License :: OSI Approved :: MIT License
Classifier: Operating System :: OS Independent
Classifier: Development Status :: 4 - Beta
Classifier: Intended Audience :: Science/Research
Requires-Python: >=3.13
License-File: LICENSE
Requires-Dist: pyserial>=3.5
Requires-Dist: xlsxwriter>=3.2.9
Dynamic: license-file
